etl_pipeline/__init__.py
etl_pipeline/etl_pipeline.py
etl_pipeline-0.0.2.dist-info/LICENSE.txt
etl_pipeline-0.0.2.dist-info/METADATA
etl_pipeline-0.0.2.dist-info/WHEEL
etl_pipeline-0.0.2.dist-info/top_level.txt
etl_pipeline-0.0.2.dist-info/RECORD
