Metadata-Version: 2.1
Name: etl-pipeline
Version: 0.0.2
Summary: package for performing etl processing on csv files
Home-page: UNKNOWN
Author: Rinesh P R
Author-email: rineshpr90@gmail.com
License: UNKNOWN
Platform: UNKNOWN
Classifier: Programming Language :: Python :: 3.5
Classifier: License :: OSI Approved :: MIT License
Classifier: Operating System :: OS Independent
